twinify/__init__.py
twinify/base.py
twinify/dataframe_data.py
twinify/illustrate.py
twinify/mst.py
twinify/serialization.py
twinify/version.py
twinify/cli/__init__.py
twinify/cli/__main__.py
twinify/cli/dpvi_loader.py
twinify/cli/dpvi_numpyro_model_loading.py
twinify/cli/napsu_loader.py
twinify/cli/preprocessing_model.py
twinify/cli/tools/__init__.py
twinify/cli/tools/__main__.py
twinify/cli/tools/check_model.py
twinify/dpvi/__init__.py
twinify/dpvi/dpvi_model.py
twinify/dpvi/dpvi_result.py
twinify/dpvi/sampling.py
twinify/dpvi/modelling/__init__.py
twinify/dpvi/modelling/automodel.py
twinify/dpvi/modelling/mixture_model.py
twinify/dpvi/modelling/na_model.py
twinify/dpvi/modelling/utils.py
twinify/napsu_mq/__init__.py
twinify/napsu_mq/junction_tree.py
twinify/napsu_mq/log_factor.py
twinify/napsu_mq/marginal_query.py
twinify/napsu_mq/markov_network.py
twinify/napsu_mq/maximum_entropy_inference.py
twinify/napsu_mq/maximum_entropy_model.py
twinify/napsu_mq/napsu_mq.py
twinify/napsu_mq/privacy_accounting.py
twinify/napsu_mq/rubins_rules.py
twinify/napsu_mq/undirected_graph.py
twinify/napsu_mq/utils.py
twinify/napsu_mq/private_pgm/__init__.py
twinify/napsu_mq/private_pgm/callbacks.py
twinify/napsu_mq/private_pgm/clique_vector.py
twinify/napsu_mq/private_pgm/dataset.py
twinify/napsu_mq/private_pgm/domain.py
twinify/napsu_mq/private_pgm/factor.py
twinify/napsu_mq/private_pgm/graphical_model.py
twinify/napsu_mq/private_pgm/inference.py
twinify/napsu_mq/private_pgm/junction_tree.py
twinify-2.0.0.dist-info/METADATA
twinify-2.0.0.dist-info/WHEEL
twinify-2.0.0.dist-info/entry_points.txt
twinify-2.0.0.dist-info/top_level.txt
twinify-2.0.0.dist-info/RECORD
