Metadata-Version: 2.1
Name: twinify
Version: 2.0.0
Summary: A software package for privacy-preserving generation of a synthetic twin to a given sensitive data set.
Home-page: https://github.com/DPBayes/twinify
Author: twinify Developers
Author-email: lukas.m.prediger@aalto.fi
Classifier: Programming Language :: Python :: 3
Classifier: License :: OSI Approved :: Apache Software License
Classifier: Operating System :: OS Independent
Classifier: Development Status :: 4 - Beta
Classifier: Intended Audience :: Science/Research
Requires-Python: >=3.7
Requires-Dist: pandas (<2.0,>=1.3.4)
Requires-Dist: d3p (<1.0,>=0.2.0)
Requires-Dist: tqdm (<5.0,>=4.62)
Requires-Dist: numpy (<2.0,>=1.21)
Requires-Dist: graphviz (<1.0.0,>=0.20.1)
Requires-Dist: arviz (<1.0.0,>=0.12.1)
Requires-Dist: networkx (<3.0.0,>=2.6.0)
Requires-Dist: disjoint-set (<1.0.0,>=0.7.0)
Provides-Extra: compatible-dependencies
Requires-Dist: d3p[compatible-dependencies] ; extra == 'compatible-dependencies'
Provides-Extra: cpu
Requires-Dist: d3p[cpu] ; extra == 'cpu'
Provides-Extra: cuda
Requires-Dist: d3p[cuda] ; extra == 'cuda'
Provides-Extra: dev
Requires-Dist: pytest ; extra == 'dev'
Provides-Extra: examples
Requires-Dist: xlrd (<2.0) ; extra == 'examples'
Requires-Dist: scikit-learn ; extra == 'examples'
Requires-Dist: openpyxl ; extra == 'examples'
